django_commands/__init__.py
django_commands/apps.py
django_commands/models.py
django_commands/management/__init__.py
django_commands/management/commands/__init__.py
django_commands/management/commands/generate_types.py
django_commands/management/commands/migration_checkpoint.py
django_commands/management/commands/migration_restore.py
django_commands/management/commands/process_urls.py
django_commands/migrations/0001_initial.py
django_commands/migrations/0002_migrationcheckpoint_create.py
django_commands/migrations/0003_alter_migrationcheckpoint_name.py
django_commands/migrations/__init__.py
samsteady_django_commands-1.0.11.dist-info/METADATA
samsteady_django_commands-1.0.11.dist-info/WHEEL
samsteady_django_commands-1.0.11.dist-info/top_level.txt
samsteady_django_commands-1.0.11.dist-info/RECORD
